{
	"levels": [
		{
			"number": "0",
			"name": "Cadet Training",
            "issue":"Trapped animal",
            "specialPoints": 0,
			"requiredServices": [
                {
                    "service":"Fire Brigade",
                    "ifFails":"Because the Fire Brigade was not called, the cat has remained stuck in the tree.",
                    "ifPresent":""
                },
                {
                    "service":"Police",
                    "ifFails":"Because the Fire Brigade was not called, the cat has remained stuck in the tree.",
                    "ifPresent":""
                }
            ]
		},
		{
			"number": "1",
			"name": "Lost Down The Bottle",
            "issue":"Trapped animal",
            "specialPoints": 5,
			"requiredServices": [
                {
                    "service":"Fire Brigade",
                    "isCritical":"false",
                    "ifFails":"Because the Fire Brigade was not called, the cat has remained stuck in the tree.",
                    "ifPresent":"Fire Brigade save cat!"
                },
                {
                    "service":"Police",
                    "isCritical":"false",
                    "ifFails":"Because the Police were not called, the cat has died.",
                    "ifPresent":"Police save cat!"
                },
                {
                    "service":"Ambulance",
                    "isCritical":"true",
                    "ifFails":"911 Operator fails to save wounded child",
                    "ifPresent":"Hero dispatch operator saves hurt child"
                }
            ]
		},
		{
			"number": "2",
			"name": "Dooty Doot",
            "issue":"Testing",
            "specialPoints": 5,
			"requiredServices": [
                {
                    "service":"Fire Brigade",
                    "isCritical": "true",
                    "ifFails":"Because the Fire Brigade was not called, the cat has remained stuck in the tree.",
                    "ifPresent":"Yay you're a hero"
                }
            ]
		},
		{
			"number": "3",
			"name": "Pizza For One",
			"requiredServices": [
                {
                    "service":"Fire Brigade",
                    "ifFails":"Because the Fire Brigade was not called, the cat has remained stuck in the tree."
                }
            ]
		},
		{
			"number": "4",
			"name": "Day 4",
			"requiredServices": [
                {
                    "service":"Fire Brigade",
                    "ifFails":"Because the Fire Brigade was not called, the cat has remained stuck in the tree."
                }
            ]
		},
		{
			"number": "5",
			"name": "Day 5",
			"requiredServices": [
                {
                    "service":"Fire Brigade",
                    "ifFails":"Because the Fire Brigade was not called, the cat has remained stuck in the tree."
                }
            ]
		},
		{
			"number": "6",
			"name": "Day 6",
			"requiredServices": [
                {
                    "service":"Fire Brigade",
                    "ifFails":"Because the Fire Brigade was not called, the cat has remained stuck in the tree."
                }
            ]
		},
		{
			"number": "7",
			"name": "Day 7",
			"requiredServices": [
                {
                    "service":"Fire Brigade",
                    "ifFails":"Because the Fire Brigade was not called, the cat has remained stuck in the tree."
                }
            ]
		},
		{
			"number": "8",
			"name": "Day 8",
			"requiredServices": [
                {
                    "service":"Fire Brigade",
                    "ifFails":"Because the Fire Brigade was not called, the cat has remained stuck in the tree."
                }
            ]
		},
		{
			"number": "9",
			"name": "Day 9",
			"requiredServices": [
                {
                    "service":"Fire Brigade",
                    "ifFails":"Because the Fire Brigade was not called, the cat has remained stuck in the tree."
                }
            ]
		},
		{
			"number": "10",
			"name": "Day 10",
			"requiredServices": [
                {
                    "service":"Fire Brigade",
                    "ifFails":"Because the Fire Brigade was not called, the cat has remained stuck in the tree."
                }
            ]
		}
	]
	
}